COPYRIGHT.txt
LICENSE.txt
MANIFEST.in
README.rst
setup.cfg
setup.py
robotframework_rfdoc.egg-info/PKG-INFO
robotframework_rfdoc.egg-info/SOURCES.txt
robotframework_rfdoc.egg-info/dependency_links.txt
robotframework_rfdoc.egg-info/requires.txt
robotframework_rfdoc.egg-info/top_level.txt
src/rfdoc/__init__.py
src/rfdoc/manage.py
src/rfdoc/rfdoc_wsgi.py
src/rfdoc/rfdocsettings_defaults.py
src/rfdoc/settings.py
src/rfdoc/upload.py
src/rfdoc/urls.py
src/rfdoc/version.py
src/rfdoc/rfdocapp/__init__.py
src/rfdoc/rfdocapp/admin.py
src/rfdoc/rfdocapp/models.py
src/rfdoc/rfdocapp/tests.py
src/rfdoc/rfdocapp/static/default.css
src/rfdoc/rfdocapp/static/jquery-1.11.0.min.js
src/rfdoc/rfdocapp/static/print.css
src/rfdoc/rfdocapp/static/rfdoc.js
src/rfdoc/rfdocapp/templates/404.html
src/rfdoc/rfdocapp/templates/500.html
src/rfdoc/rfdocapp/templates/base.html
src/rfdoc/rfdocapp/templates/index.html
src/rfdoc/rfdocapp/templates/library.html
src/rfdoc/rfdocapp/templates/search.html
src/rfdoc/rfdocapp/templates/search_form.html
src/rfdoc/rfdocapp/templates/upload.html
src/rfdoc/rfdocapp/templatetags/__init__.py
src/rfdoc/rfdocapp/templatetags/rfdoc_filters.py
src/rfdoc/rfdocapp/utils/__init__.py
src/rfdoc/rfdocapp/utils/robot_htmlutils.py
src/rfdoc/rfdocapp/views/__init__.py
src/rfdoc/rfdocapp/views/index.py
src/rfdoc/rfdocapp/views/library.py
src/rfdoc/rfdocapp/views/search.py
src/rfdoc/rfdocapp/views/upload.py