Metadata-Version: 1.1
Name: robotframework-rfdoc
Version: 0.5
Summary: Web-based Robot Framework library documentation server
Home-page: http://code.google.com/p/rfdoc/
Author: Robot Framework Developers
Author-email: robotframework-devel@googlegroups.com
License: Apache License 2.0
Keywords: robotframework testing testautomation documentation
Platform: any
Classifier: Development Status :: 5 - Production/Stable
Classifier: License :: OSI Approved :: Apache Software License
Classifier: Operating System :: OS Independent
Classifier: Programming Language :: Python
Classifier: Topic :: Software Development :: Testing
